{
  "type": "auth/StdTx",
  "value": {
    "msg": [
      {
        "type": "cosmos-sdk/MsgCreateValidator",
        "value": {
          "description": {
            "moniker": "validator1",
            "identity": "",
            "website": "",
            "details": ""
          },
          "commission": {
            "rate": "0.100000000000000000",
            "max_rate": "0.200000000000000000",
            "max_change_rate": "0.010000000000000000"
          },
          "min_self_delegation": "1",
          "delegator_address": "cosmos1m4jwlltm6swplvgm08twgs5a25khgs9gyyruav",
          "validator_address": "cosmosvaloper1m4jwlltm6swplvgm08twgs5a25khgs9gpshf3l",
          "pubkey": "cosmosvalconspub1zcjduepq8nq7dsqydyaj8hwq7r8e9k0thvesgn609cwjxmd0vkk46svp7q5qhlllzn",
          "value": {
            "denom": "altg",
            "amount": "500000000"
          }
        }
      }
    ],
    "fee": {
      "amount": [],
      "gas": "200000"
    },
    "signatures": [
      {
        "pub_key": {
          "type": "tendermint/PubKeySecp256k1",
          "value": "A9t7fRhrovP0jcCl/zi/gjHwIKkdHLFfN2qEFgSrCoDP"
        },
        "signature": "l7ujgjED/1Fdv4HPAXqSeUl/d/ApGPGQayErGfEebEVwlNBk1+zdZHjyeL2Vt5u1vYtoMJslXklrwdPsYI6dMA=="
      }
    ],
    "memo": "3c43f4c6abc43c82aeeab338f13e7a56d8451486@159.65.74.76:26656"
  }
}
